setup.cfg
setup.py
src/restify/__init__.py
src/restify/manager.py
src/restify.egg-info/PKG-INFO
src/restify.egg-info/SOURCES.txt
src/restify.egg-info/dependency_links.txt
src/restify.egg-info/requires.txt
src/restify.egg-info/top_level.txt
src/restify.egg-info/zip-safe
src/restify/dsn/__init__.py
src/restify/dsn/base.py
src/restify/dsn/sentry.py
src/restify/routing/__init__.py
src/restify/routing/base.py
src/restify/util/__init__.py