Metadata-Version: 1.1
Name: restify
Version: 0.0.4
Summary: Base wrappers for creating a REST API with Bottle
Home-page: http://glow.dev.ramcloud.io/sjohnson/rest-api-template
Author: Sean Johnson
Author-email: sean.johnson@maio.me
License: Unlicense
Platform: UNKNOWN
Classifier: Development Status :: 3 - Alpha
Classifier: Topic :: Software Development :: Libraries
Classifier: Topic :: Software Development :: Libraries :: Python Modules
